{"timestamp":"2026-03-19T06:40:14.311494Z","source":"Angel One SmartAPI via GitHub Actions","indices":{"NIFTY50":{"ltp":23233.05,"chg":-2.29,"close":23777.8},"BANKNIFTY":{"ltp":53914.75,"chg":-2.55,"close":55326.05},"NIFTYIT":{"ltp":5209.8,"chg":-2.19,"close":5326.35},"MIDCPNIFTY":{"ltp":64200.25,"chg":-2.24,"close":65668.5}},"movers":{"gainers":[{"symbol":"ADANIENT","ltp":1949.5,"chg":0.0,"series":"EQ"},{"symbol":"LT","ltp":3442.0,"chg":0.0,"series":"EQ"},{"symbol":"INFY","ltp":1235.0,"chg":0.0,"series":"EQ"},{"symbol":"ITC","ltp":300.65,"chg":0.0,"series":"EQ"},{"symbol":"SBIN","ltp":1050.0,"chg":0.0,"series":"EQ"},{"symbol":"SUNPHARMA","ltp":1761.6,"chg":0.0,"series":"EQ"},{"symbol":"TCS","ltp":2380.6,"chg":0.0,"series":"EQ"},{"symbol":"BHARTIARTL","ltp":1848.4,"chg":0.0,"series":"EQ"},{"symbol":"MARUTI","ltp":12604.0,"chg":0.0,"series":"EQ"},{"symbol":"RELIANCE","ltp":1398.7,"chg":0.0,"series":"EQ"}],"losers":[{"symbol":"KOTAKBANK","ltp":368.65,"chg":0.0,"series":"EQ"},{"symbol":"TITAN","ltp":4074.7,"chg":0.0,"series":"EQ"},{"symbol":"NESTLEIND","ltp":1181.9,"chg":0.0,"series":"EQ"},{"symbol":"HCLTECH","ltp":1330.1,"chg":0.0,"series":"EQ"},{"symbol":"WIPRO","ltp":189.35,"chg":0.0,"series":"EQ"},{"symbol":"ICICIBANK","ltp":1267.6,"chg":0.0,"series":"EQ"},{"symbol":"BAJFINANCE","ltp":842.25,"chg":0.0,"series":"EQ"},{"symbol":"ASIANPAINT","ltp":2193.8,"chg":0.0,"series":"EQ"},{"symbol":"HDFCBANK","ltp":810.5,"chg":0.0,"series":"EQ"},{"symbol":"RELIANCE","ltp":1398.7,"chg":0.0,"series":"EQ"}]},"fo":{}}