{"timestamp":"2026-02-26T09:10:46.433453Z","source":"Angel One SmartAPI via GitHub Actions","indices":{"NIFTY50":{"ltp":25477.7,"chg":-0.02,"close":25482.5},"BANKNIFTY":{"ltp":61070.0,"chg":0.04,"close":61043.35},"NIFTYIT":{"ltp":5616.95,"chg":0.04,"close":5614.85},"MIDCPNIFTY":{"ltp":70364.0,"chg":-0.05,"close":70399.25}},"movers":{"gainers":[{"symbol":"ADANIENT","ltp":2209.2,"chg":0.0,"series":"EQ"},{"symbol":"LT","ltp":4304.0,"chg":0.0,"series":"EQ"},{"symbol":"INFY","ltp":1291.0,"chg":0.0,"series":"EQ"},{"symbol":"ITC","ltp":319.75,"chg":0.0,"series":"EQ"},{"symbol":"SBIN","ltp":1207.5,"chg":0.0,"series":"EQ"},{"symbol":"SUNPHARMA","ltp":1780.2,"chg":0.0,"series":"EQ"},{"symbol":"TCS","ltp":2649.0,"chg":0.0,"series":"EQ"},{"symbol":"BHARTIARTL","ltp":1922.8,"chg":0.0,"series":"EQ"},{"symbol":"MARUTI","ltp":15179.0,"chg":0.0,"series":"EQ"},{"symbol":"RELIANCE","ltp":1406.0,"chg":0.0,"series":"EQ"}],"losers":[{"symbol":"KOTAKBANK","ltp":423.25,"chg":0.0,"series":"EQ"},{"symbol":"TITAN","ltp":4338.0,"chg":0.0,"series":"EQ"},{"symbol":"NESTLEIND","ltp":1312.9,"chg":0.0,"series":"EQ"},{"symbol":"HCLTECH","ltp":1374.0,"chg":0.0,"series":"EQ"},{"symbol":"WIPRO","ltp":200.36,"chg":0.0,"series":"EQ"},{"symbol":"ICICIBANK","ltp":1406.1,"chg":0.0,"series":"EQ"},{"symbol":"BAJFINANCE","ltp":1013.4,"chg":0.0,"series":"EQ"},{"symbol":"ASIANPAINT","ltp":2388.5,"chg":0.0,"series":"EQ"},{"symbol":"HDFCBANK","ltp":900.15,"chg":0.0,"series":"EQ"},{"symbol":"RELIANCE","ltp":1406.0,"chg":0.0,"series":"EQ"}]},"fo":{}}